setup.py
flask_alcohol/__init__.py
flask_alcohol.egg-info/PKG-INFO
flask_alcohol.egg-info/SOURCES.txt
flask_alcohol.egg-info/dependency_links.txt
flask_alcohol.egg-info/not-zip-safe
flask_alcohol.egg-info/requires.txt
flask_alcohol.egg-info/top_level.txt