Metadata-Version: 1.0
Name: flask-alcohol
Version: 0.1
Summary: Automatically generate API routes from Flask-SQLAlchemy models
Home-page: https://github.com/natfoster82/flask-alcohol
Author: Nat Foster
Author-email: nat.foster@gmail.com
License: BSD
Platform: UNKNOWN
